// === CUSTOMIZABLE VARIABLES =========================================

// Which worker (1st, 8th etc) should scout and try to find enemy base
#SCOUT_IS_NTH_WORKER=8

// When supply is bigger than N, then start auto-producing supply units
#AUTO_SUPPLY_MANAGER_WHEN_SUPPLY_EXCEEDS=25

// If have empty slot for a worker, force to build new workers
#AUTO_PRODUCE_WORKERS_MIN_SUPPLY=1

// Max number of workers for workers auto-production to remain active
#AUTO_PRODUCE_WORKERS_MAX_WORKERS=60

// === Raw build order used - taken from Liquipedia or so =============

/**
http://wiki.teamliquid.net/starcraft/2_Gate_Range_Expand
8 - Pylon (Scout)
10 - Gateway
12 - Assimilator
13 - Cybernetics Core
15 - Pylon
17 - Dragoon Range[2]
18 - Gateway
20 - Nexus[3]
20 - Dragoon
22 - Dragoon
24 - Pylon[4]
25 - 2 Dragoons
31 - Robotics Facility
*/

// === Build order for Atlantis =======================================

@ - Name - Modifier
8 - Pylon
10 - Gateway
12 - Assimilator
13 - Dragoon
15 - Cybernetics Core
15 - Pylon
17 - Dragoon Range
18 - Gateway
;20 - Nexus
20 - Gateway
20 - Dragoon
22 - Dragoon
24 - Pylon
Dragoons - x3
26 - Robotics Facility

Dragoon - x3
Observatory
Observer
Dragoon - x3
Observer

50 - Robotics Support Bay
Reaver
90 - Observer

Dragoon - x10

//27 - Robotics Support Bay
//27 - Observatory
//28 - Reaver
//28 - Observer
//31 - Reaver
//33 - Reaver
//35 - Reaver
