// === CUSTOMIZABLE VARIABLES =========================================

// Which worker (1st, 8th etc) should scout and try to find enemy base
#SCOUT_IS_NTH_WORKER=9

// When supply is bigger than N, then start auto-producing supply units
#AUTO_SUPPLY_MANAGER_WHEN_SUPPLY_EXCEEDS=28

// If have empty slot for a worker, force to build new workers
#AUTO_PRODUCE_WORKERS_MIN_SUPPLY=1

// Max number of workers for workers auto-production to remain active
#AUTO_PRODUCE_WORKERS_MAX_WORKERS=55

// === Raw build order used - taken from Liquipedia or so =============

/**
Zealot Core Zealot


8 - Pylon
10 - Gateway
13 - Zealot
14 - Assimilator
16 - Pylon
16 - Cybernetics Core
20 - Dragoon
21 - Gateway
24 - Pylon
*/

// === Build order for Atlantis =======================================

@ - Name - Modifier
8 - Pylon
10 - Gateway
13 - Zealot
14 - Assimilator
16 - Pylon
17 - Cybernetics Core
20 - Dragoon
21 - Gateway
24 - Pylon
