// === CUSTOMIZABLE VARIABLES =========================================

// Which worker (1st, 8th etc) should scout and try to find enemy base
#SCOUT_IS_NTH_WORKER=24

// When supply is bigger than N, then start auto-producing supply units
#AUTO_SUPPLY_MANAGER_WHEN_SUPPLY_EXCEEDS=25

// If have empty slot for a worker, force to build new workers
#AUTO_PRODUCE_WORKERS_MIN_WORKERS=1

// Max number of workers for workers auto-production to remain active
#AUTO_PRODUCE_WORKERS_MAX_WORKERS=60

// === Raw build order used - taken from Liquipedia or so =============

/**
https://liquipedia.net/starcraft/2_Rax_Academy_(vs._Zerg)
9/10 - Supply Depot
11/18 - Barracks
13/18 - Barracks
14/18 - Supply Depot
18/26 - Refinery
19/26 - Academy
24/26 - Supply Depot
26/34 - Stim Pack
28/34 - Comsat Station
*/

// === Build order for Atlantis =======================================

@ - Name - Modifier
9 - Supply Depot
11 - Barracks
13 - Barracks
14 - Supply Depot
24 - Supply Depot
27 - Academy
//28 - Stim Packs
28 - Refinery
33 - Barracks
35 - Comsat Station
//36 - U 238 Shells
//40 - Barracks
38 - Factory
//42 - Tank
//46 - Tank
42 - Starport
45 - Wraith
47 - Wraith
49 - Wraith
51 - Wraith
53 - Tank Siege Mode
53 - Wraith
55 - Wraith
57 - Wraith
59 - Wraith