// === CUSTOMIZABLE VARIABLES =========================================

// Which worker (1st, 8th etc) should scout and try to find enemy base
#SCOUT_IS_NTH_WORKER=8

// When supply is bigger than N, then start auto-producing supply units
#USE_AUTO_SUPPLY_MANAGER_WHEN_SUPPLY_EXCEEDS=30

// === Raw build order used - taken from Liquipedia or so =============

/**
http://wiki.teamliquid.net/starcraft/1_Fact_FE_(vs._Terran)
# 9/10 - Supply Depot
# 12/18 - Barracks
# 12/18 - Refinery
# 15/18 - Supply Depot
# 16/26 - Factory
# 20/26 - Machine Shop
# 22/26 - Siege Tank and Siege Mode
# 23/26 - Supply Depot
# 28/34 - Command Center
# 28/44 - Supply Depot
# 32/54 - Factory
*/

// === Build order for Atlantis =======================================

@ - Name - Modifier
9 - Supply Depot
12 - Barracks
12 - Refinery
13 - Marine
//15 - Marine
14 - Bunker - NATURAL
15 - Supply Depot
