// === CUSTOMIZABLE VARIABLES =========================================

// Which worker (1st, 8th etc) should scout and try to find enemy base
#SCOUT_IS_NTH_WORKER=10

// When supply is bigger than N, then start auto-producing supply units
#AUTO_SUPPLY_MANAGER_WHEN_SUPPLY_EXCEEDS=29

// If have empty slot for a worker, force to build new workers
#AUTO_PRODUCE_WORKERS_MIN_SUPPLY=1

// Max number of workers for workers auto-production to remain active
#AUTO_PRODUCE_WORKERS_MAX_WORKERS=60

// === Raw build order used - taken from Liquipedia or so =============

/**
https://liquipedia.net/starcraft/2_Rax_Academy_(vs._Zerg)
9/10 - Supply Depot
11/18 - Barracks
13/18 - Barracks
14/18 - Supply Depot
18/26 - Refinery
19/26 - Academy
24/26 - Supply Depot
26/34 - Stim Pack
28/34 - Comsat Station
*/

// === Build order for Atlantis =======================================

@ - Name - Modifier
9 - Supply Depot
11 - Barracks
14 - Supply Depot
14 - Barracks
//18 - Bunker - @MAIN_CHOKE
21 - Bunker - @MAIN
23 - Academy
22 - Supply Depot
28 - Refinery
33 - Comsat Station
35 - Factory
38 - Stim Packs
39 - Vulture
40 - Machine Shop
41 - U 238 Shells
42 - Tank
42 - Engineering Bay
54 - Tank Siege Mode
54 - Missile Turret
55 - Tank
55 - Factory
62 - Starport
64 - Wraith
66 - Science Facility
68 - Factory
69 - Physics Lab
72 - Control Tower
73 - Science Vessel
78 - Science Vessel
82 - Irradiate
81 - Wraith
84 - Science Vessel

