// === CUSTOMIZABLE VARIABLES =========================================

// Which worker (1st, 8th etc) should scout and try to find enemy base
#SCOUT_IS_NTH_WORKER=12

// When supply is bigger than N, then start auto-producing supply units
#AUTO_SUPPLY_MANAGER_WHEN_SUPPLY_EXCEEDS=24

// If have empty slot for a worker, force to build new workers
#AUTO_PRODUCE_WORKERS_MIN_SUPPLY=1

// Max number of workers for workers auto-production to remain active
#AUTO_PRODUCE_WORKERS_MAX_WORKERS=60

// === Raw build order used - taken from Liquipedia or so =============

/**
https://liquipedia.net/starcraft/Sparks_Terran
9/10 Supply Depot
11/18 Barracks
13/18 Barracks
Constant Marine production
12/18~ Scout
15/18 Supply Depot
20/26 Refinery
24/26 Academy (see note)
27 Barracks
*/

// === Build order for Atlantis =======================================

@ - Name - Modifier
9 - Supply Depot
11 - Barracks
13 - Barracks
15 - Supply Depot
20 - Refinery
24 - Academy
25 - Supply Depot
26 - MISSION:ATTACK
27 - Barracks
